Workbook

Sheet 说明
A1: 研究框架与数据口径
A3: 本研究构建黄金（GC=F）与比特币（BTC-USD）作为避险与抗通胀资产的量化比较框架，覆盖2021年7月5日至2026年7月5日共五年回测区间。黄金期货来自COMEX（Yahoo Finance），比特币来自CoinMarketCap/Yahoo Finance整合数据，两者按交易日对齐进行多资产分析。
A4: 数据口径说明： - 黄金期货为CME COMEX近月连续合约，5天交易周，共1,257个交易日； - 比特币为7×24连续交易，Yahoo Finance日线收盘价，共1,826个自然日； - 多资产指标（相关性、共同收益）基于日期内连接后的共同交易日，比特币周末数据不在对齐范围内； - 收益率统一按对数收益率计算；波动率年化系数√252； - 无风险利率假设为0（聚焦资产间横向比较，非绝对夏普）； - 指标全部为Excel公式驱动，修改「参数」sheet的滚动窗口参数可联动重算； - 原始数据在各自资产sheet中完整保留，可逐行复核。
A5: ［溯源：ev-s-20260705-745a-1、ev-s-20260705-745a-39］
A7: 关键行情变化点明细
A9: 关键宏观与行业事件
A11: 回测局限性与注意事项
A13: 本回测底稿存在以下局限性：
A14: 1. 日期对齐损失：比特币7×24连续交易，黄金仅工作日交易。多资产指标基于日期内连接，比特币周末的价格变动未纳入共同交易日分析，可能低估比特币的实际波动率并影响相关性估计。
A15: 2. 交易成本未计：黄金期货涉及展期成本和保证金要求，比特币现货涉及交易所手续费和滑点，两者均未在回测中考虑，实际可实现的收益低于底稿数值。
A16: 3. 无风险利率假设：本底稿无风险利率设为0，夏普比率为简化计算，不适合与其他资产类别的绝对夏普横向比较，仅适用于黄金与比特币之间的相对比较。
A17: 4. 事件覆盖缺口：2021年7-11月期间无收录宏观或行业事件，期间9个变化点缺乏事件归因；2024年8月BTC大幅回撤（-20.9%）缺乏对应事件解释；2026年1-3月黄金极端行情（单日-11.37%、区间-17.2%）亦无事件支撑，可能反映数据异常或上游事件库缺口。
... A20: ［溯源：ev-s-20260705-745a-1、ev-s-20260705-745a-2、ev-s-20260705-745a-3、ev-s-20260705-745a-39］

Sheet 黄金期货
A1: 日期 | B1: 开盘 | C1: 最高 | D1: 最低 | E1: 收盘 | F1: 成交量
A2: 2021-07-06 | B2: 1786.7 | C2: 1809.8 | D2: 1786.7 | E2: 1793.5 | F2: 332
A3: 2021-07-07 | B3: 1798.7 | C3: 1808.4 | D3: 1797.2 | E3: 1801.5 | F3: 244
A4: 2021-07-08 | B4: 1797 | C4: 1818.5 | D4: 1797 | E4: 1799.6 | F4: 148
A5: 2021-07-09 | B5: 1803.6 | C5: 1810.1 | D5: 1798.8 | E5: 1810 | F5: 218
A6: 2021-07-12 | B6: 1802.6 | C6: 1805.5 | D6: 1799.5 | E6: 1805.5 | F6: 147
A7: 2021-07-13 | B7: 1808.1 | C7: 1812 | D7: 1800.6 | E7: 1809.4 | F7: 78
A8: 2021-07-14 | B8: 1813.1 | C8: 1829 | D8: 1813.1 | E8: 1824.3 | F8: 707
A9: 2021-07-15 | B9: 1831.6 | C9: 1833 | D9: 1823.4 | E9: 1828.4 | F9: 99
A10: 2021-07-16 | B10: 1830.1 | C10: 1831.4 | D10: 1814.5 | E10: 1814.5 | F10: 78
A11: 2021-07-19 | B11: 1803.3 | C11: 1813.4 | D11: 1803.3 | E11: 1808.7 | F11: 33
A12: 2021-07-20 | B12: 1812.9 | C12: 1824 | D12: 1810.9 | E12: 1810.9 | F12: 128
A13: 2021-07-21 | B13: 1807 | C13: 1807 | D13: 1800 | E13: 1802.9 | F13: 135
... A1258: 2026-07-03 | B1258: 4138 | C1258: 4208.2998 | D1258: 4133.7998 | E1258: 4187.2998 | F1258: 54673

Sheet 比特币现货
A1: 日期 | B1: 开盘 | C1: 最高 | D1: 最低 | E1: 收盘 | F1: 成交量
A2: 2021-07-05 | B2: 35284.344 | C2: 35284.344 | D2: 33213.66 | E2: 33746.004 | F2: 26721554282
A3: 2021-07-06 | B3: 33723.508 | C3: 35038.535 | D3: 33599.918 | E3: 34235.195 | F3: 26501259870
A4: 2021-07-07 | B4: 34225.68 | C4: 34997.664 | D4: 33839.289 | E4: 33855.328 | F4: 24796027477
A5: 2021-07-08 | B5: 33889.605 | C5: 33907.906 | D5: 32133.184 | E5: 32877.371 | F5: 29910396946
A6: 2021-07-09 | B6: 32861.672 | C6: 34042.293 | D6: 32318.881 | E6: 33798.012 | F6: 27436021028
A7: 2021-07-10 | B7: 33811.242 | C7: 34209.07 | D7: 33116.012 | E7: 33520.52 | F7: 22971873468
A8: 2021-07-11 | B8: 33509.078 | C8: 34584.703 | D8: 33346.738 | E8: 34240.188 | F8: 20108729370
A9: 2021-07-12 | B9: 34254.016 | C9: 34592.156 | D9: 32697.309 | E9: 33155.848 | F9: 24321499537
A10: 2021-07-13 | B10: 33125.469 | C10: 33327.102 | D10: 32261.42 | E10: 32702.025 | F10: 19120856669
A11: 2021-07-14 | B11: 32723.846 | C11: 33061.398 | D11: 31639.125 | E11: 32822.348 | F11: 21376531210
A12: 2021-07-15 | B12: 32827.875 | C12: 33159.641 | D12: 31175.709 | E12: 31780.73 | F12: 21300524237
A13: 2021-07-16 | B13: 31841.551 | C13: 32218.406 | D13: 31100.674 | E13: 31421.539 | F13: 23699476918
... A1827: 2026-07-05 | B1827: 63087.742 | C1827: 63087.742 | D1827: 62576.273 | E1827: 62965.289 | F1827: 17628848128

Sheet 参数
A1: 参数 | B1: 值 | C1: 说明
A2: 滚动窗口（交易日） | B2: 30 | C2: 改动后指标sheet的滚动波动率联动重算
A3: 年化系数 | B3: 252 | C3: 波动率年化用，√年化系数

Sheet 对齐
A1: 日期 | B1: 黄金 GC=F收盘 | C1: 比特币 BTC-USD收盘
A2: 2021-07-06 | B2: 1793.5 | C2: 34235.195
A3: 2021-07-07 | B3: 1801.5 | C3: 33855.328
A4: 2021-07-08 | B4: 1799.6 | C4: 32877.371
A5: 2021-07-09 | B5: 1810 | C5: 33798.012
A6: 2021-07-12 | B6: 1805.5 | C6: 33155.848
A7: 2021-07-13 | B7: 1809.4 | C7: 32702.025
A8: 2021-07-14 | B8: 1824.3 | C8: 32822.348
A9: 2021-07-15 | B9: 1828.4 | C9: 31780.73
A10: 2021-07-16 | B10: 1814.5 | C10: 31421.539
A11: 2021-07-19 | B11: 1808.7 | C11: 30817.832
A12: 2021-07-20 | B12: 1810.9 | C12: 29807.348
A13: 2021-07-21 | B13: 1802.9 | C13: 32110.693
... A1258: 2026-07-03 | B1258: 4187.2998 | C1258: 62544.199

Sheet 指标
A1: 日期 | B1: 黄金 GC=F日收益 | C1: 黄金 GC=F净值(=100) | D1: 黄金 GC=F回撤 | E1: 黄金 GC=F滚动年化波动 | F1: 比特币 BTC-USD日收益 | G1: 比特币 BTC-USD净值(=100) | H1: 比特币 BTC-USD回撤 | I1: 比特币 BTC-USD滚动年化波动
A2: ='对齐'!A2 | C2: ='对齐'!B2/'对齐'!B$2*100 | D2: ='对齐'!B2/MAX('对齐'!B$2:'对齐'!B2)-1 | E2: =IF(ROW()-2>='参数'!$B$2,STDEV(OFFSET(B2,1-'参数'!$B$2,0,'参数'!$B$2,1))*SQRT('参数'!$B$3),"") | G2: ='对齐'!C2/'对齐'!C$2*100 | H2: ='对齐'!C2/MAX('对齐'!C$2:'对齐'!C2)-1 | I2: =IF(ROW()-2>='参数'!$B$2,STDEV(OFFSET(F2,1-'参数'!$B$2,0,'参数'!$B$2,1))*SQRT('参数'!$B$3),"")
A3: ='对齐'!A3 | B3: ='对齐'!B3/'对齐'!B2-1 | C3: ='对齐'!B3/'对齐'!B$2*100 | D3: ='对齐'!B3/MAX('对齐'!B$2:'对齐'!B3)-1 | E3: =IF(ROW()-2>='参数'!$B$2,STDEV(OFFSET(B3,1-'参数'!$B$2,0,'参数'!$B$2,1))*SQRT('参数'!$B$3),"") | F3: ='对齐'!C3/'对齐'!C2-1 | G3: ='对齐'!C3/'对齐'!C$2*100 | H3: ='对齐'!C3/MAX('对齐'!C$2:'对齐'!C3)-1 | I3: =IF(ROW()-2>='参数'!$B$2,STDEV(OFFSET(F3,1-'参数'!$B$2,0,'参数'!$B$2,1))*SQRT('参数'!$B$3),"")
A4: ='对齐'!A4 | B4: ='对齐'!B4/'对齐'!B3-1 | C4: ='对齐'!B4/'对齐'!B$2*100 | D4: ='对齐'!B4/MAX('对齐'!B$2:'对齐'!B4)-1 | E4: =IF(ROW()-2>='参数'!$B$2,STDEV(OFFSET(B4,1-'参数'!$B$2,0,'参数'!$B$2,1))*SQRT('参数'!$B$3),"") | F4: ='对齐'!C4/'对齐'!C3-1 | G4: ='对齐'!C4/'对齐'!C$2*100 | H4: ='对齐'!C4/MAX('对齐'!C$2:'对齐'!C4)-1 | I4: =IF(ROW()-2>='参数'!$B$2,STDEV(OFFSET(F4,1-'参数'!$B$2,0,'参数'!$B$2,1))*SQRT('参数'!$B$3),"")
A5: ='对齐'!A5 | B5: ='对齐'!B5/'对齐'!B4-1 | C5: ='对齐'!B5/'对齐'!B$2*100 | D5: ='对齐'!B5/MAX('对齐'!B$2:'对齐'!B5)-1 | E5: =IF(ROW()-2>='参数'!$B$2,STDEV(OFFSET(B5,1-'参数'!$B$2,0,'参数'!$B$2,1))*SQRT('参数'!$B$3),"") | F5: ='对齐'!C5/'对齐'!C4-1 | G5: ='对齐'!C5/'对齐'!C$2*100 | H5: ='对齐'!C5/MAX('对齐'!C$2:'对齐'!C5)-1 | I5: =IF(ROW()-2>='参数'!$B$2,STDEV(OFFSET(F5,1-'参数'!$B$2,0,'参数'!$B$2,1))*SQRT('参数'!$B$3),"")
A6: ='对齐'!A6 | B6: ='对齐'!B6/'对齐'!B5-1 | C6: ='对齐'!B6/'对齐'!B$2*100 | D6: ='对齐'!B6/MAX('对齐'!B$2:'对齐'!B6)-1 | E6: =IF(ROW()-2>='参数'!$B$2,STDEV(OFFSET(B6,1-'参数'!$B$2,0,'参数'!$B$2,1))*SQRT('参数'!$B$3),"") | F6: ='对齐'!C6/'对齐'!C5-1 | G6: ='对齐'!C6/'对齐'!C$2*100 | H6: ='对齐'!C6/MAX('对齐'!C$2:'对齐'!C6)-1 | I6: =IF(ROW()-2>='参数'!$B$2,STDEV(OFFSET(F6,1-'参数'!$B$2,0,'参数'!$B$2,1))*SQRT('参数'!$B$3),"")
A7: ='对齐'!A7 | B7: ='对齐'!B7/'对齐'!B6-1 | C7: ='对齐'!B7/'对齐'!B$2*100 | D7: ='对齐'!B7/MAX('对齐'!B$2:'对齐'!B7)-1 | E7: =IF(ROW()-2>='参数'!$B$2,STDEV(OFFSET(B7,1-'参数'!$B$2,0,'参数'!$B$2,1))*SQRT('参数'!$B$3),"") | F7: ='对齐'!C7/'对齐'!C6-1 | G7: ='对齐'!C7/'对齐'!C$2*100 | H7: ='对齐'!C7/MAX('对齐'!C$2:'对齐'!C7)-1 | I7: =IF(ROW()-2>='参数'!$B$2,STDEV(OFFSET(F7,1-'参数'!$B$2,0,'参数'!$B$2,1))*SQRT('参数'!$B$3),"")
A8: ='对齐'!A8 | B8: ='对齐'!B8/'对齐'!B7-1 | C8: ='对齐'!B8/'对齐'!B$2*100 | D8: ='对齐'!B8/MAX('对齐'!B$2:'对齐'!B8)-1 | E8: =IF(ROW()-2>='参数'!$B$2,STDEV(OFFSET(B8,1-'参数'!$B$2,0,'参数'!$B$2,1))*SQRT('参数'!$B$3),"") | F8: ='对齐'!C8/'对齐'!C7-1 | G8: ='对齐'!C8/'对齐'!C$2*100 | H8: ='对齐'!C8/MAX('对齐'!C$2:'对齐'!C8)-1 | I8: =IF(ROW()-2>='参数'!$B$2,STDEV(OFFSET(F8,1-'参数'!$B$2,0,'参数'!$B$2,1))*SQRT('参数'!$B$3),"")
A9: ='对齐'!A9 | B9: ='对齐'!B9/'对齐'!B8-1 | C9: ='对齐'!B9/'对齐'!B$2*100 | D9: ='对齐'!B9/MAX('对齐'!B$2:'对齐'!B9)-1 | E9: =IF(ROW()-2>='参数'!$B$2,STDEV(OFFSET(B9,1-'参数'!$B$2,0,'参数'!$B$2,1))*SQRT('参数'!$B$3),"") | F9: ='对齐'!C9/'对齐'!C8-1 | G9: ='对齐'!C9/'对齐'!C$2*100 | H9: ='对齐'!C9/MAX('对齐'!C$2:'对齐'!C9)-1 | I9: =IF(ROW()-2>='参数'!$B$2,STDEV(OFFSET(F9,1-'参数'!$B$2,0,'参数'!$B$2,1))*SQRT('参数'!$B$3),"")
A10: ='对齐'!A10 | B10: ='对齐'!B10/'对齐'!B9-1 | C10: ='对齐'!B10/'对齐'!B$2*100 | D10: ='对齐'!B10/MAX('对齐'!B$2:'对齐'!B10)-1 | E10: =IF(ROW()-2>='参数'!$B$2,STDEV(OFFSET(B10,1-'参数'!$B$2,0,'参数'!$B$2,1))*SQRT('参数'!$B$3),"") | F10: ='对齐'!C10/'对齐'!C9-1 | G10: ='对齐'!C10/'对齐'!C$2*100 | H10: ='对齐'!C10/MAX('对齐'!C$2:'对齐'!C10)-1 | I10: =IF(ROW()-2>='参数'!$B$2,STDEV(OFFSET(F10,1-'参数'!$B$2,0,'参数'!$B$2,1))*SQRT('参数'!$B$3),"")
A11: ='对齐'!A11 | B11: ='对齐'!B11/'对齐'!B10-1 | C11: ='对齐'!B11/'对齐'!B$2*100 | D11: ='对齐'!B11/MAX('对齐'!B$2:'对齐'!B11)-1 | E11: =IF(ROW()-2>='参数'!$B$2,STDEV(OFFSET(B11,1-'参数'!$B$2,0,'参数'!$B$2,1))*SQRT('参数'!$B$3),"") | F11: ='对齐'!C11/'对齐'!C10-1 | G11: ='对齐'!C11/'对齐'!C$2*100 | H11: ='对齐'!C11/MAX('对齐'!C$2:'对齐'!C11)-1 | I11: =IF(ROW()-2>='参数'!$B$2,STDEV(OFFSET(F11,1-'参数'!$B$2,0,'参数'!$B$2,1))*SQRT('参数'!$B$3),"")
A12: ='对齐'!A12 | B12: ='对齐'!B12/'对齐'!B11-1 | C12: ='对齐'!B12/'对齐'!B$2*100 | D12: ='对齐'!B12/MAX('对齐'!B$2:'对齐'!B12)-1 | E12: =IF(ROW()-2>='参数'!$B$2,STDEV(OFFSET(B12,1-'参数'!$B$2,0,'参数'!$B$2,1))*SQRT('参数'!$B$3),"") | F12: ='对齐'!C12/'对齐'!C11-1 | G12: ='对齐'!C12/'对齐'!C$2*100 | H12: ='对齐'!C12/MAX('对齐'!C$2:'对齐'!C12)-1 | I12: =IF(ROW()-2>='参数'!$B$2,STDEV(OFFSET(F12,1-'参数'!$B$2,0,'参数'!$B$2,1))*SQRT('参数'!$B$3),"")
A13: ='对齐'!A13 | B13: ='对齐'!B13/'对齐'!B12-1 | C13: ='对齐'!B13/'对齐'!B$2*100 | D13: ='对齐'!B13/MAX('对齐'!B$2:'对齐'!B13)-1 | E13: =IF(ROW()-2>='参数'!$B$2,STDEV(OFFSET(B13,1-'参数'!$B$2,0,'参数'!$B$2,1))*SQRT('参数'!$B$3),"") | F13: ='对齐'!C13/'对齐'!C12-1 | G13: ='对齐'!C13/'对齐'!C$2*100 | H13: ='对齐'!C13/MAX('对齐'!C$2:'对齐'!C13)-1 | I13: =IF(ROW()-2>='参数'!$B$2,STDEV(OFFSET(F13,1-'参数'!$B$2,0,'参数'!$B$2,1))*SQRT('参数'!$B$3),"")
A14: ='对齐'!A14 | B14: ='对齐'!B14/'对齐'!B13-1 | C14: ='对齐'!B14/'对齐'!B$2*100 | D14: ='对齐'!B14/MAX('对齐'!B$2:'对齐'!B14)-1 | E14: =IF(ROW()-2>='参数'!$B$2,STDEV(OFFSET(B14,1-'参数'!$B$2,0,'参数'!$B$2,1))*SQRT('参数'!$B$3),"") | F14: ='对齐'!C14/'对齐'!C13-1 | G14: ='对齐'!C14/'对齐'!C$2*100 | H14: ='对齐'!C14/MAX('对齐'!C$2:'对齐'!C14)-1 | I14: =IF(ROW()-2>='参数'!$B$2,STDEV(OFFSET(F14,1-'参数'!$B$2,0,'参数'!$B$2,1))*SQRT('参数'!$B$3),"")
... A1258: ='对齐'!A1258 | B1258: ='对齐'!B1258/'对齐'!B1257-1 | C1258: ='对齐'!B1258/'对齐'!B$2*100 | D1258: ='对齐'!B1258/MAX('对齐'!B$2:'对齐'!B1258)-1 | E1258: =IF(ROW()-2>='参数'!$B$2,STDEV(OFFSET(B1258,1-'参数'!$B$2,0,'参数'!$B$2,1))*SQRT('参数'!$B$3),"") | F1258: ='对齐'!C1258/'对齐'!C1257-1 | G1258: ='对齐'!C1258/'对齐'!C$2*100 | H1258: ='对齐'!C1258/MAX('对齐'!C$2:'对齐'!C1258)-1 | I1258: =IF(ROW()-2>='参数'!$B$2,STDEV(OFFSET(F1258,1-'参数'!$B$2,0,'参数'!$B$2,1))*SQRT('参数'!$B$3),"")

Sheet 汇总
A1: 指标 | B1: 黄金 GC=F | C1: 比特币 BTC-USD
A2: 区间总收益 | B2: ='对齐'!B1258/'对齐'!B2-1 | C2: ='对齐'!C1258/'对齐'!C2-1
A3: 年化收益率（CAGR） | B3: =POWER('对齐'!B1258/'对齐'!B2,'参数'!$B$3/1256)-1 | C3: =POWER('对齐'!C1258/'对齐'!C2,'参数'!$B$3/1256)-1
A4: 年化波动率（全样本） | B4: =STDEV('指标'!B3:B1258)*SQRT('参数'!$B$3) | C4: =STDEV('指标'!F3:F1258)*SQRT('参数'!$B$3)
A5: 夏普比率（rf=0） | B5: =B3/B4 | C5: =C3/C4
A6: 最大回撤 | B6: =MIN('指标'!D3:D1258) | C6: =MIN('指标'!H3:H1258)
A7: 正收益天数占比 | B7: =COUNTIF('指标'!B3:B1258,">0")/COUNT('指标'!B3:B1258) | C7: =COUNTIF('指标'!F3:F1258,">0")/COUNT('指标'!F3:F1258)
A8: 日收益相关系数 | B8: =CORREL('指标'!B3:B1258,'指标'!F3:F1258)

Sheet 年度收益
A1: 年份 | B1: 黄金 GC=F收益 | C1: 比特币 BTC-USD收益 | D1: 差额（比特币 BTC-USD−黄金 GC=F）
A2: 2021 | B2: ='对齐'!B127/'对齐'!B2-1 | C2: ='对齐'!C127/'对齐'!C2-1 | D2: =C2-B2
A3: 2022 | B3: ='对齐'!B378/'对齐'!B127-1 | C3: ='对齐'!C378/'对齐'!C127-1 | D3: =C3-B3
A4: 2023 | B4: ='对齐'!B628/'对齐'!B378-1 | C4: ='对齐'!C628/'对齐'!C378-1 | D4: =C4-B4
A5: 2024 | B5: ='对齐'!B880/'对齐'!B628-1 | C5: ='对齐'!C880/'对齐'!C628-1 | D5: =C5-B5
A6: 2025 | B6: ='对齐'!B1132/'对齐'!B880-1 | C6: ='对齐'!C1132/'对齐'!C880-1 | D6: =C6-B6
A7: 2026 | B7: ='对齐'!B1258/'对齐'!B1132-1 | C7: ='对齐'!C1258/'对齐'!C1132-1 | D7: =C7-B7
A8: 全周期 | B8: ='对齐'!B1258/'对齐'!B2-1 | C8: ='对齐'!C1258/'对齐'!C2-1 | D8: =C8-B8
A10: 注：年度收益以上一年最后共同交易日收盘为基准（首年度以区间首日为基准）；首末年度可能为区间内的部分年度。

Sheet 图表

Sheet 黄金与比特币关键行情变化点（规则触发，按日期排列）
A1: 日期 | B1: 标的 | C1: 类型 | D1: 触发规则 | E1: 严重度 | F1: 触发窗口
A2: 2021-09-20 | B2: BTC | C2: drawdown | D2: 自 2021-09-06 高点回撤 -18.6%（确认级） | E2: 3 | F2: 2021-09-06 → 2021-09-20
A3: 2022-02-28 | B3: BTC | C3: rally | D3: 自 2022-02-21 低点反弹 +16.5%（确认级） | E3: 3 | F3: 2022-02-21 → 2022-02-28
A4: 2022-03-07 | B4: 黄金 | C4: rally | D4: 自 2021-09-29 低点反弹 +15.8%（确认级） | E4: 3 | F4: 2021-09-29 → 2022-03-07
A5: 2022-07-11 | B5: 黄金 | C5: drawdown | D5: 自 2022-03-08 高点回撤 -15.2%（确认级） | E5: 3 | F5: 2022-03-08 → 2022-07-11
A6: 2022-11-08 | B6: BTC | C6: accel_down | D6: 单日收益 -10.01%，前21日分布 -5.4σ；量能异常 3.3× | E6: 3 | F6: 2022-10-18 → 2022-11-08
A7: 2022-12-01 | B7: 黄金 | C7: accel_up | D7: 单日收益 +3.16%，前21日分布 +2.8σ；量能异常 140.5× | E7: 3 | F7: 2022-11-01 → 2022-12-01
A8: 2023-03-13 | B8: BTC | C8: rally | D8: 自 2023-03-10 低点反弹 +19.9%（确认级） | E8: 3 | F8: 2023-03-10 → 2023-03-13
A9: 2023-06-21 | B9: BTC | C9: rally | D9: 自 2023-06-14 低点反弹 +19.5%（确认级） | E9: 3 | F9: 2023-06-14 → 2023-06-21
A10: 2024-08-23 | B10: BTC | C10: rally | D10: 自 2024-08-05 低点反弹 +18.7%（确认级） | E10: 3 | F10: 2024-08-05 → 2024-08-23
A11: 2024-09-19 | B11: BTC | C11: rally | D11: 自 2024-09-06 低点反弹 +16.7%（确认级） | E11: 3 | F11: 2024-09-06 → 2024-09-19
A12: 2024-11-06 | B12: BTC | C12: accel_up | D12: 单日收益 +9.05%，前21日分布 +4.8σ；量能异常 3.8× | E12: 3 | F12: 2024-10-16 → 2024-11-06
... A17: 2026-03-23 | B17: 黄金 | C17: drawdown | D17: 自 2026-01-29 高点回撤 -17.2%（确认级）；量能异常 22.5× | E17: 3 | F17: 2026-01-29 → 2026-03-23
A19: 溯源：ev-s-20260705-745a-2、ev-s-20260705-745a-3

Sheet 2021-2026年影响黄金与比特币的关键宏观与行业事件
A1: 日期 | B1: 事件 | C1: 类别 | D1: 方向 | E1: 行情影响 | F1: 评级
A2: 2022-02-24 | B2: 俄罗斯全面入侵乌克兰 | C2: 地缘政治 | D2: ⬆ | E2: 黄金飙升，BTC先跌后涨 | F2: 5
A3: 2022-03-16 | B3: 美联储启动加息周期 | C3: 宏观 | D3: ⬇ | E3: 风险资产承压，黄金受美元走强压制 | F3: 5
A4: 2022-07-13 | B4: 美国CPI 9.1%创40年新高 | C4: 宏观 | D4: ↕ | E4: 通胀对冲需求推升黄金，BTC先涨后跌 | F4: 5
A5: 2022-09-21 | B5: 美联储连续第三次加息75bp | C5: 宏观 | D5: ⬇ | E5: 全球风险资产下跌，BTC跌破$19k | F5: 5
A6: 2022-11-02 | B6: FTX崩盘 | C6: 行业 | D6: ⬇ | E6: BTC暴跌，黄金受益于避险资金流入 | F6: 5
A7: 2023-03-10 | B7: 硅谷银行倒闭 | C7: 宏观 | D7: ⬆ | E7: 黄金突破$2000，BTC先跌后涨 | F7: 5
A8: 2023-03-19 | B8: 瑞信被UBS收购 | C8: 宏观 | D8: ⬆ | E8: 黄金创年内新高，BTC反弹至$28k | F8: 5
A9: 2023-06-15 | B9: BlackRock提交BTC ETF申请 | C9: 行业 | D9: ⬆ | E9: BTC从$25k反弹至$31k | F9: 5
A10: 2023-10-07 | B10: 哈马斯突袭以色列 | C10: 地缘政治 | D10: ⬆ | E10: 黄金从$1820飙升至$2000+ | F10: 5
A11: 2024-01-10 | B11: SEC批准11只现货BTC ETF | C11: 行业 | D11: ⬆ | E11: BTC从$45k飙升至$73k | F11: 5
A12: 2024-08-23 | B12: 鲍威尔Jackson Hole释放降息信号 | C12: 宏观 | D12: ⬆ | E12: 黄金突破$2500创新高，BTC反弹 | F12: 5
... A17: 2026-06-05 | B17: BTC跌破$60,000 | C17: 行业 | D17: ⬇ | E17: 资金转向AI和IPO | F17: 5
A19: 溯源：ev-s-20260705-745a-11、ev-s-20260705-745a-15、ev-s-20260705-745a-16、ev-s-20260705-745a-19、ev-s-20260705-745a-4、ev-s-20260705-745a-6、ev-s-20260705-745a-21、ev-s-20260705-745a-24、ev-s-20260705-745a-26、ev-s-20260705-745a-9、ev-s-20260705-745a-27、ev-s-20260705-745a-31、ev-s-20260705-745a-32、ev-s-20260705-745a-10、ev-s-20260705-745a-33

Sheet 溯源
A1: evidence_id | B1: 类型 | C1: 来源URL | D1: 抓取时间 | E1: 查询 | F1: 摘录
A2: ev-s-20260705-745a-1 | B2: market_data | C2: https://query2.finance.yahoo.com/v8/finance/chart/GC=F?period1=1625443200&period2=1783296000&interval=1d&events=history | D2: 2026-07-05T08:16:06+00:00 | E2: {'ticker': 'GC=F', 'start': '2021-07-05', 'end': '2026-07-05', 'source': 'Yahoo Finance (query2)'} | F2: 1257 行日线，2021-07-06 至 2026-07-03，来源 Yahoo Finance (query2)
A3: ev-s-20260705-745a-2 | B3: computation | C3: evidence:ev-s-20260705-745a-39 | D3: 2026-07-05T08:16:14+00:00 | E3: {'params': {'trend_window': 20, 'trend_min_slope': 0.001, 'zscore_window': 21, 'zscore_threshold': 2.0, 'swing_threshold': 0.15, 'volume_window': 60, 'volume_multiple': 3.0, 'merge_window_days': 10}, 'rows': 1826} | F3: 208 个变化点：2021-07-24 rally(s3)；2021-07-26 trend_up(s1)；2021-09-07 accel_down(s2)；2021-09-10 trend_down(s1)；2021-09-20 accel_down(s2)；2021-09-20 drawdown(s3)；2021-10-01 accel_up(s2)；2021-10-01 rally(s3)
A4: ev-s-20260705-745a-3 | B4: computation | C4: evidence:ev-s-20260705-745a-1 | D4: 2026-07-05T08:16:14+00:00 | E4: {'params': {'trend_window': 20, 'trend_min_slope': 0.001, 'zscore_window': 21, 'zscore_threshold': 2.0, 'swing_threshold': 0.15, 'volume_window': 60, 'volume_multiple': 3.0, 'merge_window_days': 10}, 'rows': 1257} | F4: 117 个变化点：2021-08-06 accel_down(s2)；2021-08-31 trend_up(s1)；2021-09-16 accel_down(s2)；2021-09-20 trend_down(s2)；2021-09-30 accel_up(s3)；2021-10-13 accel_up(s2)；2021-10-20 trend_up(s1)；2021-11-04 accel_up(s2)
A5: ev-s-20260705-745a-4 | B5: search | C5: https://tokentax.co/blog/ftx-collapse | D5: 2026-07-05T08:18:20+00:00 | E5: {'query': 'FTX collapse date November 2022', 'backend': 'tavily', 'max_results': 5} | F5: The FTX Collapse: A Complete Guide；Bankruptcy of FTX；The FTX Collapse: A Complete Guide | CoinLedger；Sam Bankman-Fried and FTX: The Timeline of the Collapse；[PDF] The collapse of FTX - KPMG agentic corporate services
A6: ev-s-20260705-745a-5 | B6: search | C6: https://www.history.com/this-day-in-history/november-30/chatgpt-released-openai | D6: 2026-07-05T08:18:21+00:00 | E6: {'query': 'ChatGPT release date November 2022', 'backend': 'tavily', 'max_results': 5} | F6: ChatGPT, the generative AI chatbot, is released - History.com；ChatGPT - Wikipedia；Q about before Nov 30 2022 : r/ChatGPT - Reddit；ChatGPT had its initial public release November 30th, 2022. That's 820 days to t...；Timeline Of ChatGPT Updates & Key Events
A7: ev-s-20260705-745a-6 | B7: search | C7: https://en.wikipedia.org/wiki/Collapse_of_Silicon_Valley_Bank | D7: 2026-07-05T08:18:21+00:00 | E7: {'query': 'Silicon Valley Bank collapse date March 2023', 'backend': 'tavily', 'max_results': 5} | F7: Collapse of Silicon Valley Bank - Wikipedia；Collapse of Silicon Valley Bank | History | Research Starters | EBSCO Research；The Failure of Silicon Valley Bank and the Panic of 2023 | Yale Department of Economics；The Silicon Valley Bank Collapse | March 14, 2023；The Failure of Silicon Valley Bank and the Panic of 2023 - American Economic Association
A8: ev-s-20260705-745a-7 | B8: search | C8: https://en.wikipedia.org/wiki/DeepSeek | D8: 2026-07-05T08:18:29+00:00 | E8: {'query': 'DeepSeek AI launch date January 2025', 'backend': 'tavily', 'max_results': 5} | F8: DeepSeek；DeepSeek | Rise, Technologies, Impact, & Global Response；Explainer: What is DeepSeek and why is it disrupting the AI sector?；The January 2025 release of a low-cost generative AI ...；Timeline of DeepSeek
A9: ev-s-20260705-745a-8 | B9: search | C9: https://www.lseg.com/en/ftse-russell/research/bitcoin-halving | D9: 2026-07-05T08:18:36+00:00 | E9: {'query': 'Bitcoin halving 2024 date', 'backend': 'tavily', 'max_results': 5} | F9: Bitcoin halving 2024 | LSEG；Bitcoin Halving Countdown；Bitcoin Halving 2024: Everything You Need to Know | IG International；2024 Bitcoin Halving: One Year Later；Bitcoin Halving Dates: Investor’s Guide 2026 | CoinLedger
A10: ev-s-20260705-745a-9 | B10: search | C10: https://bitbo.io/calendar/etfs | D10: 2026-07-05T08:18:37+00:00 | E10: {'query': 'Bitcoin ETF SEC approval date January 2024', 'backend': 'tavily', 'max_results': 5} | F10: Bitcoin ETF Approval Date History；SEC Greenlights Bitcoin ETFs: What Happened and What It Portends | Foley & Lardner；SEC Approves Eleven Spot Bitcoin Exchange Traded Funds (ETFs)；SEC Approves Bitcoin Exchange-Traded Products (ETPs)；Bitcoin ETF: SEC approval one year on - Compliance Corylated
A11: ev-s-20260705-745a-10 | B11: search | C11: https://www.klgates.com/President-Trump-Announces-Reciprocal-Tariffs-Beginning-5-April-2025-4-2-2025 | D11: 2026-07-05T08:18:37+00:00 | E11: {'query': 'Trump tariff announcement April 2025', 'backend': 'tavily', 'max_results': 5} | F11: President Trump Announces "Reciprocal" Tariffs Beginning 5 April 2025 | HUB | K&L Gates；Modifying Reciprocal Tariff Rates to Reflect Trading Partner ...；Regulating Imports with a Reciprocal Tariff to Rectify Trade Practices ...；Liberation Day tariffs - Wikipedia；Remarks Announcing Additional United States Tariff Actions on Foreign Imports | The American Presidency Project
A12: ev-s-20260705-745a-11 | B12: search | C12: https://www.huri.harvard.edu/russo-ukrainian-war | D12: 2026-07-05T08:18:37+00:00 | E12: {'query': 'Russia Ukraine war start date February 2022', 'backend': 'tavily', 'max_results': 5} | F12: Russo-Ukrainian War | Ukrainian Research Institute；When did the Russia-Ukraine War begin? | Britannica；Russia Ukraine War - February 2022 Recap Documentary；Russia's invasion of Ukraine, initiated on February 24, 2022, is ...；Russia invades Ukraine | HISTORY
... A40: ev-s-20260705-745a-39 | B40: market_data | C40: https://query2.finance.yahoo.com/v8/finance/chart/BTC-USD?period1=1625443200&period2=1783296000&interval=1d&events=history | D40: 2026-07-05T08:16:06+00:00 | E40: {'ticker': 'BTC-USD', 'start': '2021-07-05', 'end': '2026-07-05', 'source': 'Yahoo Finance (query2)'} | F40: 1826 行日线，2021-07-05 至 2026-07-05，来源 Yahoo Finance (query2)
